INSTALL.rst
LICENSE
MANIFEST.in
README.rst
setup.py
bin/capitalizr
capitalizr/__init__.py
capitalizr.egg-info/PKG-INFO
capitalizr.egg-info/SOURCES.txt
capitalizr.egg-info/dependency_links.txt
capitalizr.egg-info/not-zip-safe
capitalizr.egg-info/top_level.txt
doc/capitalizr.1.gz