Metadata-Version: 1.0
Name: capitalizr
Version: 1.02.00
Summary: capitalizr changes the case of first letter of any word (lowercase to uppercase)
Home-page: https://github.com/santosh/capitalizr
Author: Santosh Kumar
Author-email: sntshkmr60@gmail.com
License: capitalizr - changes the case (lowercase to uppercase) the first letter of
